template_reverse/__init__.py
pytemplate_reverse-0.0.3.dist-info/LICENSE
pytemplate_reverse-0.0.3.dist-info/METADATA
pytemplate_reverse-0.0.3.dist-info/WHEEL
pytemplate_reverse-0.0.3.dist-info/top_level.txt
pytemplate_reverse-0.0.3.dist-info/RECORD
