Metadata-Version: 2.1
Name: pytemplate-reverse
Version: 0.0.3
Summary: Reverse-engineer the values of a string based on a template
Home-page: https://github.com/yvdlima/pytemplate-reverse
Author: Yuri Vinicius Didone de Lima
Author-email: yuri.vdl@gmail.com
License: MIT License
Platform: UNKNOWN
Classifier: Programming Language :: Python :: 3
Classifier: License :: OSI Approved :: MIT License
Classifier: Operating System :: OS Independent
Requires-Python: >=3
